fullmetal_utils/__init__.py
fullmetal_utils-0.0.1.dist-info/LICENSE
fullmetal_utils-0.0.1.dist-info/METADATA
fullmetal_utils-0.0.1.dist-info/WHEEL
fullmetal_utils-0.0.1.dist-info/entry_points.txt
fullmetal_utils-0.0.1.dist-info/top_level.txt
fullmetal_utils-0.0.1.dist-info/RECORD
