Metadata-Version: 2.1
Name: fullmetal-utils
Version: 0.0.1
Summary: Utilities for editing SQL databases
Author-email: Odos Matthews <odosmatthews@gmail.com>
License: The MIT License (MIT)
Project-URL: Homepage, https://github.com/eddiethedean/fullmetal_utils
Keywords: sql,utils,sqlalchemy
Classifier: License :: OSI Approved :: MIT License
Classifier: Programming Language :: Python
Classifier: Programming Language :: Python :: 3
Requires-Python: >=3.9
License-File: LICENSE
Requires-Dist: SQLAlchemy
Requires-Dist: alembic
Requires-Dist: tomli ; python_version < "3.11"
Provides-Extra: dev
Requires-Dist: black ; extra == 'dev'
Requires-Dist: isort ; extra == 'dev'
Requires-Dist: pip-tools ; extra == 'dev'
Requires-Dist: pytest ; extra == 'dev'
